strypy/__init__.py
strypy/basics.py
strypy/clipboard.py
strypy/colour.py
strypy/constants.py
strypy/file.py
strypy/generator.py
strypy/sorting.py
strypy/testing.py
strypy/docs/Contributing.rst
strypy/docs/Installation.rst
strypy/docs/Makefile
strypy/docs/Testing.rst
strypy/docs/conf.py
strypy/docs/icon.ico
strypy/docs/icon.png
strypy/docs/index.rst
strypy/docs/logo.png
strypy/docs/make.bat
strypy/tests/__init__.py
strypy/tests/test.txt
strypy/tests/test_basics.py
strypy/tests/test_clipboard.py
strypy/tests/test_colour.py
strypy/tests/test_file.py
strypy/tests/test_generator.py
strypy/tests/test_sorting.py
strypy-1.0.4.dist-info/LICENSE
strypy-1.0.4.dist-info/METADATA
strypy-1.0.4.dist-info/WHEEL
strypy-1.0.4.dist-info/top_level.txt
strypy-1.0.4.dist-info/RECORD
