Metadata-Version: 2.1
Name: strypy
Version: 1.0.4
Summary: Powerful and fundamental string manipulation package
Author-email: Thomas Barry <tomb80940@gmail.com>
License: MIT License
Project-URL: Homepage, https://github.com/TomTheCodingGuy/StryPy
Project-URL: Repository, https://github.com/TomTheCodingGuy/StryPy
Project-URL: Documentation, https://strypy.readthedocs.io
Project-URL: Bug Tracker, https://github.com/TomTheCodingGuy/StryPy/issues
Keywords: string,strypy,manipulation
Classifier: License :: OSI Approved :: MIT License
Classifier: Programming Language :: Python
Classifier: Programming Language :: Python :: 3
Requires-Python: >=3.0
License-File: LICENSE
Requires-Dist: colorama
Requires-Dist: pyperclip
Requires-Dist: pytest
Provides-Extra: dev
Requires-Dist: pytest ; extra == 'dev'
